MANIFEST.in
README.md
setup.py
ievv_coderefactor/__init__.py
ievv_coderefactor/cli.py
ievv_coderefactor/colorize.py
ievv_coderefactor/directorytreewalker.py
ievv_coderefactor/file_or_directory_renamer.py
ievv_coderefactor/refactor_file.py
ievv_coderefactor/refactor_tree.py
ievv_coderefactor/refactorlogger.py
ievv_coderefactor/replacer_registry.py
ievv_coderefactor/strip_json_comments.py
ievv_coderefactor.egg-info/PKG-INFO
ievv_coderefactor.egg-info/SOURCES.txt
ievv_coderefactor.egg-info/dependency_links.txt
ievv_coderefactor.egg-info/entry_points.txt
ievv_coderefactor.egg-info/not-zip-safe
ievv_coderefactor.egg-info/requires.txt
ievv_coderefactor.egg-info/top_level.txt