Metadata-Version: 1.1
Name: ievv-coderefactor
Version: 1.0.0
Summary: General purpose code refactor solution.
Home-page: https://github.com/appressoas/ievv_coderefactor
Author: Appresso AS
Author-email: post@appresso.no
License: MIT
Platform: UNKNOWN
Classifier: Development Status :: 3 - Alpha
Classifier: Intended Audience :: Developers
Classifier: Topic :: Software Development :: Code Generators
Classifier: License :: OSI Approved
Classifier: Programming Language :: Python :: 3
Classifier: Programming Language :: Python :: 2
